{
    "_checkpoint": {
        "global_record": {
            "index": -1,
            "infractions": {
                "collisions_layout": 0.35898469285509266,
                "collisions_pedestrian": 0.0,
                "collisions_vehicle": 0.027160846199953237,
                "outside_route_lanes": 0.35898469285509266,
                "red_light": 0.14025519310067278,
                "route_dev": 0.0,
                "route_timeout": 0.0,
                "stop_infraction": 0.0,
                "vehicle_blocked": 1.4563038752477808
            },
            "meta": {
                "exceptions": [
                    [
                        "RouteScenario_7",
                        1,
                        "Failed - Agent got blocked"
                    ],
                    [
                        "RouteScenario_8",
                        2,
                        "Failed - Agent got blocked"
                    ],
                    [
                        "RouteScenario_10",
                        4,
                        "Failed - Agent got blocked"
                    ],
                    [
                        "RouteScenario_11",
                        5,
                        "Failed - Agent got blocked"
                    ],
                    [
                        "RouteScenario_12",
                        6,
                        "Failed - Agent got blocked"
                    ],
                    [
                        "RouteScenario_13",
                        7,
                        "Failed - Agent got blocked"
                    ],
                    [
                        "RouteScenario_14",
                        8,
                        "Failed - Agent got blocked"
                    ],
                    [
                        "RouteScenario_15",
                        9,
                        "Failed - Agent got blocked"
                    ],
                    [
                        "RouteScenario_31",
                        11,
                        "Failed - Agent got blocked"
                    ],
                    [
                        "RouteScenario_32",
                        12,
                        "Failed - Agent got blocked"
                    ],
                    [
                        "RouteScenario_34",
                        14,
                        "Failed - Agent got blocked"
                    ],
                    [
                        "RouteScenario_35",
                        15,
                        "Failed - Agent got blocked"
                    ],
                    [
                        "RouteScenario_36",
                        16,
                        "Failed - Agent got blocked"
                    ],
                    [
                        "RouteScenario_37",
                        17,
                        "Failed - Agent got blocked"
                    ],
                    [
                        "RouteScenario_38",
                        18,
                        "Failed - Agent got blocked"
                    ],
                    [
                        "RouteScenario_39",
                        19,
                        "Failed - Agent got blocked"
                    ]
                ]
            },
            "route_id": -1,
            "scores": {
                "score_composed": 33.04368689370947,
                "score_penalty": 0.7806173153482722,
                "score_route": 44.90664257470439
            },
            "status": "Failed"
        },
        "progress": [
            20,
            20
        ],
        "records": [
            {
                "index": 0,
                "infractions": {
                    "collisions_layout": [],
                    "collisions_pedestrian": [],
                    "collisions_vehicle": [
                        "Agent collided against object with type=vehicle.yamaha.yzf and id=13522 at (x=51.66, y=-357.583, z=0.034)",
                        "Agent collided against object with type=vehicle.yamaha.yzf and id=13522 at (x=37.366, y=-342.299, z=0.034)"
                    ],
                    "outside_route_lanes": [],
                    "red_light": [],
                    "route_dev": [],
                    "route_timeout": [],
                    "stop_infraction": [],
                    "vehicle_blocked": []
                },
                "meta": {
                    "duration_game": 530.0000078976154,
                    "duration_system": 1572.920948266983,
                    "route_length": 2628.599169102265
                },
                "route_id": "RouteScenario_6",
                "scores": {
                    "score_composed": 36.0,
                    "score_penalty": 0.36,
                    "score_route": 100.0
                },
                "status": "Completed"
            },
            {
                "index": 1,
                "infractions": {
                    "collisions_layout": [
                        "Agent collided against object with type=traffic.traffic_light and id=13731 at (x=-390.261, y=0.002, z=0.031)"
                    ],
                    "collisions_pedestrian": [],
                    "collisions_vehicle": [],
                    "outside_route_lanes": [
                        "Agent went outside its route lanes for about 3.299 meters (2.1% of the completed route)"
                    ],
                    "red_light": [
                        "Agent ran a red light 13730 at (x=-389.3, y=21.0, z=0.0)"
                    ],
                    "route_dev": [],
                    "route_timeout": [],
                    "stop_infraction": [],
                    "vehicle_blocked": [
                        "Agent got blocked at (x=-390.417, y=0.163, z=0.031)"
                    ]
                },
                "meta": {
                    "duration_game": 282.00000420212746,
                    "duration_system": 783.144834280014,
                    "route_length": 2347.6173004123057
                },
                "route_id": "RouteScenario_7",
                "scores": {
                    "score_composed": 1.4122528356497936,
                    "score_penalty": 0.4454546109448589,
                    "score_route": 3.1703630424977485
                },
                "status": "Failed - Agent got blocked"
            },
            {
                "index": 2,
                "infractions": {
                    "collisions_layout": [],
                    "collisions_pedestrian": [],
                    "collisions_vehicle": [],
                    "outside_route_lanes": [],
                    "red_light": [],
                    "route_dev": [],
                    "route_timeout": [],
                    "stop_infraction": [],
                    "vehicle_blocked": [
                        "Agent got blocked at (x=294.843, y=-246.433, z=0.038)"
                    ]
                },
                "meta": {
                    "duration_game": 187.9000027999282,
                    "duration_system": 528.1510875225067,
                    "route_length": 2091.0568061088115
                },
                "route_id": "RouteScenario_8",
                "scores": {
                    "score_composed": 1.0655800448033377,
                    "score_penalty": 1.0,
                    "score_route": 1.0655800448033377
                },
                "status": "Failed - Agent got blocked"
            },
            {
                "index": 3,
                "infractions": {
                    "collisions_layout": [],
                    "collisions_pedestrian": [],
                    "collisions_vehicle": [
                        "Agent collided against object with type=vehicle.diamondback.century and id=14442 at (x=351.452, y=39.684, z=0.309)"
                    ],
                    "outside_route_lanes": [],
                    "red_light": [],
                    "route_dev": [],
                    "route_timeout": [],
                    "stop_infraction": [],
                    "vehicle_blocked": []
                },
                "meta": {
                    "duration_game": 640.2000095397234,
                    "duration_system": 1895.447927236557,
                    "route_length": 2033.3454321744916
                },
                "route_id": "RouteScenario_9",
                "scores": {
                    "score_composed": 60.0,
                    "score_penalty": 0.6,
                    "score_route": 100.0
                },
                "status": "Completed"
            },
            {
                "index": 4,
                "infractions": {
                    "collisions_layout": [],
                    "collisions_pedestrian": [],
                    "collisions_vehicle": [
                        "Agent collided against object with type=vehicle.audi.tt and id=14890 at (x=-125.137, y=-144.196, z=0.034)"
                    ],
                    "outside_route_lanes": [],
                    "red_light": [],
                    "route_dev": [],
                    "route_timeout": [],
                    "stop_infraction": [],
                    "vehicle_blocked": [
                        "Agent got blocked at (x=16.966, y=-80.838, z=0.033)"
                    ]
                },
                "meta": {
                    "duration_game": 484.5000072196126,
                    "duration_system": 1456.6813099384308,
                    "route_length": 2150.402605037221
                },
                "route_id": "RouteScenario_10",
                "scores": {
                    "score_composed": 34.85255394812441,
                    "score_penalty": 0.6,
                    "score_route": 58.08758991354069
                },
                "status": "Failed - Agent got blocked"
            },
            {
                "index": 5,
                "infractions": {
                    "collisions_layout": [
                        "Agent collided against object with type=static.guardrail and id=0 at (x=23.454, y=-169.233, z=0.21)"
                    ],
                    "collisions_pedestrian": [],
                    "collisions_vehicle": [],
                    "outside_route_lanes": [
                        "Agent went outside its route lanes for about 2.592 meters (0.15% of the completed route)"
                    ],
                    "red_light": [],
                    "route_dev": [],
                    "route_timeout": [],
                    "stop_infraction": [],
                    "vehicle_blocked": [
                        "Agent got blocked at (x=109.672, y=-170.01, z=0.229)"
                    ]
                },
                "meta": {
                    "duration_game": 511.0500076152384,
                    "duration_system": 1531.1428501605988,
                    "route_length": 1867.2469467601286
                },
                "route_id": "RouteScenario_11",
                "scores": {
                    "score_composed": 39.70148598690259,
                    "score_penalty": 0.6489955067164588,
                    "score_route": 61.17374554373898
                },
                "status": "Failed - Agent got blocked"
            },
            {
                "index": 6,
                "infractions": {
                    "collisions_layout": [],
                    "collisions_pedestrian": [],
                    "collisions_vehicle": [],
                    "outside_route_lanes": [],
                    "red_light": [],
                    "route_dev": [],
                    "route_timeout": [],
                    "stop_infraction": [],
                    "vehicle_blocked": [
                        "Agent got blocked at (x=142.864, y=-363.685, z=0.033)"
                    ]
                },
                "meta": {
                    "duration_game": 536.7500079981983,
                    "duration_system": 1477.109807729721,
                    "route_length": 2069.435963460894
                },
                "route_id": "RouteScenario_12",
                "scores": {
                    "score_composed": 10.450768449661654,
                    "score_penalty": 1.0,
                    "score_route": 10.450768449661654
                },
                "status": "Failed - Agent got blocked"
            },
            {
                "index": 7,
                "infractions": {
                    "collisions_layout": [],
                    "collisions_pedestrian": [],
                    "collisions_vehicle": [],
                    "outside_route_lanes": [],
                    "red_light": [],
                    "route_dev": [],
                    "route_timeout": [],
                    "stop_infraction": [],
                    "vehicle_blocked": [
                        "Agent got blocked at (x=106.375, y=-354.696, z=0.033)"
                    ]
                },
                "meta": {
                    "duration_game": 589.6000087857246,
                    "duration_system": 1685.2835898399353,
                    "route_length": 2440.358324116989
                },
                "route_id": "RouteScenario_13",
                "scores": {
                    "score_composed": 57.019527819906045,
                    "score_penalty": 1.0,
                    "score_route": 57.019527819906045
                },
                "status": "Failed - Agent got blocked"
            },
            {
                "index": 8,
                "infractions": {
                    "collisions_layout": [],
                    "collisions_pedestrian": [],
                    "collisions_vehicle": [],
                    "outside_route_lanes": [],
                    "red_light": [],
                    "route_dev": [],
                    "route_timeout": [],
                    "stop_infraction": [],
                    "vehicle_blocked": [
                        "Agent got blocked at (x=311.648, y=-264.254, z=0.038)"
                    ]
                },
                "meta": {
                    "duration_game": 372.5500055514276,
                    "duration_system": 1137.8159251213074,
                    "route_length": 1862.2548302259988
                },
                "route_id": "RouteScenario_14",
                "scores": {
                    "score_composed": 10.93840458464589,
                    "score_penalty": 1.0,
                    "score_route": 10.93840458464589
                },
                "status": "Failed - Agent got blocked"
            },
            {
                "index": 9,
                "infractions": {
                    "collisions_layout": [
                        "Agent collided against object with type=traffic.speed_limit.90 and id=16275 at (x=-398.339, y=2.276, z=0.033)"
                    ],
                    "collisions_pedestrian": [],
                    "collisions_vehicle": [],
                    "outside_route_lanes": [
                        "Agent went outside its route lanes for about 4.975 meters (2.58% of the completed route)"
                    ],
                    "red_light": [],
                    "route_dev": [],
                    "route_timeout": [],
                    "stop_infraction": [],
                    "vehicle_blocked": [
                        "Agent got blocked at (x=-398.703, y=2.371, z=0.033)"
                    ]
                },
                "meta": {
                    "duration_game": 370.9000055268407,
                    "duration_system": 1010.8619766235352,
                    "route_length": 2288.1490786388968
                },
                "route_id": "RouteScenario_15",
                "scores": {
                    "score_composed": 2.7646036967892367,
                    "score_penalty": 0.6332009830555247,
                    "score_route": 4.3660761287017955
                },
                "status": "Failed - Agent got blocked"
            },
            {
                "index": 10,
                "infractions": {
                    "collisions_layout": [],
                    "collisions_pedestrian": [],
                    "collisions_vehicle": [],
                    "outside_route_lanes": [],
                    "red_light": [],
                    "route_dev": [],
                    "route_timeout": [],
                    "stop_infraction": [],
                    "vehicle_blocked": []
                },
                "meta": {
                    "duration_game": 494.70000737160444,
                    "duration_system": 1462.4405314922333,
                    "route_length": 2628.0801981075497
                },
                "route_id": "RouteScenario_30",
                "scores": {
                    "score_composed": 100.0,
                    "score_penalty": 1.0,
                    "score_route": 100.0
                },
                "status": "Completed"
            },
            {
                "index": 11,
                "infractions": {
                    "collisions_layout": [
                        "Agent collided against object with type=static.guardrail and id=0 at (x=23.998, y=-169.359, z=0.226)"
                    ],
                    "collisions_pedestrian": [],
                    "collisions_vehicle": [],
                    "outside_route_lanes": [
                        "Agent went outside its route lanes for about 2.084 meters (0.12% of the completed route)"
                    ],
                    "red_light": [
                        "Agent ran a red light 17029 at (x=-389.3, y=21.0, z=0.0)"
                    ],
                    "route_dev": [],
                    "route_timeout": [],
                    "stop_infraction": [],
                    "vehicle_blocked": [
                        "Agent got blocked at (x=109.892, y=-170.001, z=0.229)"
                    ]
                },
                "meta": {
                    "duration_game": 736.5000109747052,
                    "duration_system": 2156.05176115036,
                    "route_length": 2336.692466906927
                },
                "route_id": "RouteScenario_31",
                "scores": {
                    "score_composed": 32.9795945356953,
                    "score_penalty": 0.45445230656318397,
                    "score_route": 72.56997942227419
                },
                "status": "Failed - Agent got blocked"
            },
            {
                "index": 12,
                "infractions": {
                    "collisions_layout": [],
                    "collisions_pedestrian": [],
                    "collisions_vehicle": [],
                    "outside_route_lanes": [],
                    "red_light": [],
                    "route_dev": [],
                    "route_timeout": [],
                    "stop_infraction": [],
                    "vehicle_blocked": [
                        "Agent got blocked at (x=294.685, y=-246.427, z=0.038)"
                    ]
                },
                "meta": {
                    "duration_game": 188.0000028014183,
                    "duration_system": 498.5456910133362,
                    "route_length": 2319.9530265841654
                },
                "route_id": "RouteScenario_32",
                "scores": {
                    "score_composed": 0.9711939100157934,
                    "score_penalty": 1.0,
                    "score_route": 0.9711939100157934
                },
                "status": "Failed - Agent got blocked"
            },
            {
                "index": 13,
                "infractions": {
                    "collisions_layout": [],
                    "collisions_pedestrian": [],
                    "collisions_vehicle": [],
                    "outside_route_lanes": [],
                    "red_light": [],
                    "route_dev": [],
                    "route_timeout": [],
                    "stop_infraction": [],
                    "vehicle_blocked": []
                },
                "meta": {
                    "duration_game": 380.00000566244125,
                    "duration_system": 1156.8873450756073,
                    "route_length": 2025.3942837912246
                },
                "route_id": "RouteScenario_33",
                "scores": {
                    "score_composed": 100.0,
                    "score_penalty": 1.0,
                    "score_route": 100.0
                },
                "status": "Completed"
            },
            {
                "index": 14,
                "infractions": {
                    "collisions_layout": [],
                    "collisions_pedestrian": [],
                    "collisions_vehicle": [
                        "Agent collided against object with type=vehicle.audi.tt and id=18189 at (x=-119.361, y=-148.197, z=0.034)"
                    ],
                    "outside_route_lanes": [],
                    "red_light": [],
                    "route_dev": [],
                    "route_timeout": [],
                    "stop_infraction": [],
                    "vehicle_blocked": [
                        "Agent got blocked at (x=19.492, y=-75.465, z=0.033)"
                    ]
                },
                "meta": {
                    "duration_game": 563.5500083975494,
                    "duration_system": 1658.024738073349,
                    "route_length": 2136.987313757202
                },
                "route_id": "RouteScenario_34",
                "scores": {
                    "score_composed": 42.35740061549961,
                    "score_penalty": 0.6,
                    "score_route": 70.59566769249935
                },
                "status": "Failed - Agent got blocked"
            },
            {
                "index": 15,
                "infractions": {
                    "collisions_layout": [
                        "Agent collided against object with type=static.guardrail and id=0 at (x=22.753, y=-168.953, z=0.178)"
                    ],
                    "collisions_pedestrian": [],
                    "collisions_vehicle": [],
                    "outside_route_lanes": [
                        "Agent went outside its route lanes for about 5.752 meters (0.36% of the completed route)"
                    ],
                    "red_light": [],
                    "route_dev": [],
                    "route_timeout": [],
                    "stop_infraction": [],
                    "vehicle_blocked": [
                        "Agent got blocked at (x=41.982, y=-170.299, z=0.229)"
                    ]
                },
                "meta": {
                    "duration_game": 515.1500076763332,
                    "duration_system": 1513.074746131897,
                    "route_length": 2564.1038284200968
                },
                "route_id": "RouteScenario_35",
                "scores": {
                    "score_composed": 28.92132666439446,
                    "score_penalty": 0.6476753706382615,
                    "score_route": 44.65404734457248
                },
                "status": "Failed - Agent got blocked"
            },
            {
                "index": 16,
                "infractions": {
                    "collisions_layout": [],
                    "collisions_pedestrian": [],
                    "collisions_vehicle": [],
                    "outside_route_lanes": [],
                    "red_light": [],
                    "route_dev": [],
                    "route_timeout": [],
                    "stop_infraction": [],
                    "vehicle_blocked": [
                        "Agent got blocked at (x=109.067, y=-355.665, z=0.033)"
                    ]
                },
                "meta": {
                    "duration_game": 220.15000328049064,
                    "duration_system": 609.1159045696259,
                    "route_length": 2058.955397544899
                },
                "route_id": "RouteScenario_36",
                "scores": {
                    "score_composed": 9.809120029458967,
                    "score_penalty": 1.0,
                    "score_route": 9.809120029458967
                },
                "status": "Failed - Agent got blocked"
            },
            {
                "index": 17,
                "infractions": {
                    "collisions_layout": [],
                    "collisions_pedestrian": [],
                    "collisions_vehicle": [],
                    "outside_route_lanes": [],
                    "red_light": [],
                    "route_dev": [],
                    "route_timeout": [],
                    "stop_infraction": [],
                    "vehicle_blocked": [
                        "Agent got blocked at (x=105.669, y=-354.323, z=0.033)"
                    ]
                },
                "meta": {
                    "duration_game": 589.1500087790191,
                    "duration_system": 1714.4957146644592,
                    "route_length": 2404.6673585939084
                },
                "route_id": "RouteScenario_37",
                "scores": {
                    "score_composed": 72.3136249322959,
                    "score_penalty": 1.0,
                    "score_route": 72.3136249322959
                },
                "status": "Failed - Agent got blocked"
            },
            {
                "index": 18,
                "infractions": {
                    "collisions_layout": [],
                    "collisions_pedestrian": [],
                    "collisions_vehicle": [],
                    "outside_route_lanes": [],
                    "red_light": [],
                    "route_dev": [],
                    "route_timeout": [],
                    "stop_infraction": [],
                    "vehicle_blocked": [
                        "Agent got blocked at (x=311.682, y=-263.092, z=0.038)"
                    ]
                },
                "meta": {
                    "duration_game": 337.8500050343573,
                    "duration_system": 1044.529037475586,
                    "route_length": 1863.183155362338
                },
                "route_id": "RouteScenario_38",
                "scores": {
                    "score_composed": 16.62622328700976,
                    "score_penalty": 1.0,
                    "score_route": 16.62622328700976
                },
                "status": "Failed - Agent got blocked"
            },
            {
                "index": 19,
                "infractions": {
                    "collisions_layout": [
                        "Agent collided against object with type=static.guardrail and id=0 at (x=-396.647, y=1.971, z=0.033)"
                    ],
                    "collisions_pedestrian": [],
                    "collisions_vehicle": [],
                    "outside_route_lanes": [
                        "Agent went outside its route lanes for about 8.041 meters (4.22% of the completed route)"
                    ],
                    "red_light": [],
                    "route_dev": [],
                    "route_timeout": [],
                    "stop_infraction": [],
                    "vehicle_blocked": [
                        "Agent got blocked at (x=-397.006, y=2.115, z=0.033)"
                    ]
                },
                "meta": {
                    "duration_game": 370.5500055216253,
                    "duration_system": 1058.7677516937256,
                    "route_length": 2288.1490786388968
                },
                "route_id": "RouteScenario_39",
                "scores": {
                    "score_composed": 2.6900765333366308,
                    "score_penalty": 0.6225675290471566,
                    "score_route": 4.320939348465233
                },
                "status": "Failed - Agent got blocked"
            }
        ]
    },
    "eligible": true,
    "entry_status": "Finished with agent errors",
    "labels": [
        "Avg. driving score",
        "Avg. route completion",
        "Avg. infraction penalty",
        "Collisions with pedestrians",
        "Collisions with vehicles",
        "Collisions with layout",
        "Red lights infractions",
        "Stop sign infractions",
        "Off-road infractions",
        "Route deviations",
        "Route timeouts",
        "Agent blocked"
    ],
    "sensors": [
        "carla_camera",
        "carla_camera",
        "carla_camera",
        "carla_camera",
        "carla_lidar",
        "carla_imu",
        "carla_gnss",
        "carla_speedometer"
    ],
    "values": [
        "33.044",
        "44.907",
        "0.781",
        "0.000",
        "0.027",
        "0.359",
        "0.140",
        "0.000",
        "0.359",
        "0.000",
        "0.000",
        "1.456"
    ]
}